{
  "npmVersion": "5.0.3",
  "rushMinimumVersion": "3.0.10",
  "nodeSupportedVersionRange": ">=6.9.0 <9.0.0",
  "projectFolderMinDepth": 1,
  "gitPolicy": {
    // Require GitHub scrubbed e-mails
    "allowedEmailRegExps": [
      "[^@]+@users\\.noreply\\.github\\.com"
    ],
    "sampleEmail": "mrexample@users.noreply.github.com"
  },
  "projects": [
    {
      "packageName": "@microsoft/loader-load-themed-styles",
      "projectFolder": "loader-load-themed-styles",
      "reviewCategory": "libraries",
      "shouldPublish": true
    },
    {
      "packageName": "@microsoft/loader-set-webpack-public-path",
      "projectFolder": "loader-set-webpack-public-path",
      "reviewCategory": "libraries",
      "shouldPublish": true
    },
    {
      "packageName": "@microsoft/loader-raw-script",
      "projectFolder": "loader-raw-script",
      "reviewCategory": "libraries",
      "shouldPublish": true
    }
  ]
}