{
  "name": "@rushstack/rush-serve-plugin",
  "entries": [
    {
      "version": "0.1.9",
      "tag": "@rushstack/rush-serve-plugin_v0.1.9",
      "date": "Tue, 26 Apr 2022 00:10:15 GMT",
      "comments": {
        "dependency": [
          {
            "comment": "Updating dependency \"@rushstack/debug-certificate-manager\" to `1.1.41`"
          },
          {
            "comment": "Updating dependency \"@rushstack/heft-node-rig\" to `1.9.1`"
          }
        ]
      }
    },
    {
      "version": "0.1.8",
      "tag": "@rushstack/rush-serve-plugin_v0.1.8",
      "date": "Sat, 23 Apr 2022 02:13:06 GMT",
      "comments": {
        "dependency": [
          {
            "comment": "Updating dependency \"@rushstack/debug-certificate-manager\" to `1.1.40`"
          },
          {
            "comment": "Updating dependency \"@rushstack/node-core-library\" to `3.45.4`"
          },
          {
            "comment": "Updating dependency \"@rushstack/rig-package\" to `0.3.11`"
          },
          {
            "comment": "Updating dependency \"@rushstack/ts-command-line\" to `4.10.10`"
          },
          {
            "comment": "Updating dependency \"@rushstack/eslint-config\" to `2.6.0`"
          },
          {
            "comment": "Updating dependency \"@rushstack/heft\" to `0.45.0`"
          },
          {
            "comment": "Updating dependency \"@rushstack/heft-config-file\" to `0.8.3`"
          },
          {
            "comment": "Updating dependency \"@rushstack/heft-node-rig\" to `1.9.0`"
          }
        ]
      }
    },
    {
      "version": "0.1.7",
      "tag": "@rushstack/rush-serve-plugin_v0.1.7",
      "date": "Fri, 15 Apr 2022 00:12:36 GMT",
      "comments": {
        "dependency": [
          {
            "comment": "Updating dependency \"@rushstack/debug-certificate-manager\" to `1.1.39`"
          },
          {
            "comment": "Updating dependency \"@rushstack/node-core-library\" to `3.45.3`"
          },
          {
            "comment": "Updating dependency \"@rushstack/rig-package\" to `0.3.10`"
          },
          {
            "comment": "Updating dependency \"@rushstack/ts-command-line\" to `4.10.9`"
          },
          {
            "comment": "Updating dependency \"@rushstack/eslint-config\" to `2.5.4`"
          },
          {
            "comment": "Updating dependency \"@rushstack/heft\" to `0.44.13`"
          },
          {
            "comment": "Updating dependency \"@rushstack/heft-config-file\" to `0.8.2`"
          },
          {
            "comment": "Updating dependency \"@rushstack/heft-node-rig\" to `1.8.11`"
          }
        ]
      }
    },
    {
      "version": "0.1.6",
      "tag": "@rushstack/rush-serve-plugin_v0.1.6",
      "date": "Wed, 13 Apr 2022 15:12:41 GMT",
      "comments": {
        "dependency": [
          {
            "comment": "Updating dependency \"@rushstack/debug-certificate-manager\" to `1.1.38`"
          },
          {
            "comment": "Updating dependency \"@rushstack/heft\" to `0.44.12`"
          },
          {
            "comment": "Updating dependency \"@rushstack/heft-node-rig\" to `1.8.10`"
          }
        ]
      }
    },
    {
      "version": "0.1.5",
      "tag": "@rushstack/rush-serve-plugin_v0.1.5",
      "date": "Tue, 12 Apr 2022 23:29:34 GMT",
      "comments": {
        "patch": [
          {
            "comment": "Include rush-plugin-manifest.json in published files."
          }
        ],
        "dependency": [
          {
            "comment": "Updating dependency \"@rushstack/debug-certificate-manager\" to `1.1.37`"
          },
          {
            "comment": "Updating dependency \"@rushstack/heft\" to `0.44.11`"
          },
          {
            "comment": "Updating dependency \"@rushstack/heft-node-rig\" to `1.8.9`"
          }
        ]
      }
    },
    {
      "version": "0.1.4",
      "tag": "@rushstack/rush-serve-plugin_v0.1.4",
      "date": "Tue, 12 Apr 2022 02:58:32 GMT",
      "comments": {
        "dependency": [
          {
            "comment": "Updating dependency \"@rushstack/debug-certificate-manager\" to `1.1.36`"
          },
          {
            "comment": "Updating dependency \"@rushstack/heft\" to `0.44.10`"
          },
          {
            "comment": "Updating dependency \"@rushstack/heft-node-rig\" to `1.8.8`"
          }
        ]
      }
    },
    {
      "version": "0.1.3",
      "tag": "@rushstack/rush-serve-plugin_v0.1.3",
      "date": "Sat, 09 Apr 2022 19:07:48 GMT",
      "comments": {
        "dependency": [
          {
            "comment": "Updating dependency \"@rushstack/debug-certificate-manager\" to `1.1.35`"
          },
          {
            "comment": "Updating dependency \"@rushstack/heft\" to `0.44.9`"
          },
          {
            "comment": "Updating dependency \"@rushstack/heft-node-rig\" to `1.8.7`"
          }
        ]
      }
    },
    {
      "version": "0.1.2",
      "tag": "@rushstack/rush-serve-plugin_v0.1.2",
      "date": "Sat, 09 Apr 2022 02:24:27 GMT",
      "comments": {
        "dependency": [
          {
            "comment": "Updating dependency \"@rushstack/debug-certificate-manager\" to `1.1.34`"
          },
          {
            "comment": "Updating dependency \"@rushstack/node-core-library\" to `3.45.2`"
          },
          {
            "comment": "Updating dependency \"@rushstack/rig-package\" to `0.3.9`"
          },
          {
            "comment": "Updating dependency \"@rushstack/ts-command-line\" to `4.10.8`"
          },
          {
            "comment": "Updating dependency \"@rushstack/eslint-config\" to `2.5.3`"
          },
          {
            "comment": "Updating dependency \"@rushstack/heft\" to `0.44.8`"
          },
          {
            "comment": "Updating dependency \"@rushstack/heft-config-file\" to `0.8.1`"
          },
          {
            "comment": "Updating dependency \"@rushstack/heft-node-rig\" to `1.8.6`"
          }
        ]
      }
    },
    {
      "version": "0.1.1",
      "tag": "@rushstack/rush-serve-plugin_v0.1.1",
      "date": "Fri, 08 Apr 2022 20:05:59 GMT",
      "comments": {
        "dependency": [
          {
            "comment": "Updating dependency \"@rushstack/debug-certificate-manager\" to `1.1.33`"
          },
          {
            "comment": "Updating dependency \"@rushstack/heft\" to `0.44.7`"
          },
          {
            "comment": "Updating dependency \"@rushstack/heft-node-rig\" to `1.8.5`"
          }
        ]
      }
    },
    {
      "version": "0.1.0",
      "tag": "@rushstack/rush-serve-plugin_v0.1.0",
      "date": "Fri, 08 Apr 2022 02:24:20 GMT",
      "comments": {
        "minor": [
          {
            "comment": "Runs a local `express` server that serves the output of selected projects when running a configured command in watch mode. Port selection is either dynamic or manually specifiable via an argument in command-line.json"
          }
        ]
      }
    }
  ]
}
